drf_multi_lookup/__init__.py
drf_multi_lookup/mixins.py
drf_multi_lookup-0.0.26.dist-info/LICENSE.md
drf_multi_lookup-0.0.26.dist-info/METADATA
drf_multi_lookup-0.0.26.dist-info/WHEEL
drf_multi_lookup-0.0.26.dist-info/top_level.txt
drf_multi_lookup-0.0.26.dist-info/RECORD
